argops-1.1.0.dist-info/METADATA
argops-1.1.0.dist-info/WHEEL
argops-1.1.0.dist-info/entry_points.txt
argops-1.1.0.dist-info/licenses/LICENSE
argops/__init__.py
argops/adapters/__init__.py
argops/adapters/argocd.py
argops/adapters/console.py
argops/adapters/git.py
argops/adapters/gitea.py
argops/entrypoints/__init__.py
argops/entrypoints/cli.py
argops/entrypoints/utils.py
argops/exceptions.py
argops/model.py
argops/py.typed
argops/services.py
argops/version.py
argops-1.1.0.dist-info/RECORD
