Metadata-Version: 2.1
Name: argops
Version: 1.1.0
Summary: Promote argo application between environments
Author-Email: Lyz <lyz@riseup.net>
License: GPL-3.0-only
Classifier: Development Status :: 2 - Pre-Alpha
Classifier: Intended Audience :: Developers
Classifier: License :: OSI Approved :: GNU General Public License v3 (GPLv3)
Classifier: Operating System :: Unix
Classifier: Operating System :: POSIX
Classifier: Programming Language :: Python
Classifier: Programming Language :: Python :: 3
Classifier: Programming Language :: Python :: 3.8
Classifier: Programming Language :: Python :: 3.9
Classifier: Programming Language :: Python :: 3.10
Classifier: Programming Language :: Python :: 3.11
Classifier: Topic :: Utilities
Classifier: Natural Language :: English
Project-URL: Issues, https://codeberg.org/lyz/argops/issues
Project-URL: homepage, https://codeberg.org/lyz/argops
Requires-Python: >=3.9.2
Requires-Dist: typer[all]>=0.9.0
Requires-Dist: GitPython>=3.1.43
Requires-Dist: ruyaml>=0.91.0
Requires-Dist: pydantic>=2.9.1
Requires-Dist: rich>=13.9.4
Requires-Dist: questionary>=2.1.0
Provides-Extra: testing
